<annotation>
	<folder>train</folder>
	<filename>IMG_20200218_2038260.jpg</filename>
	<path>C:\Users\Woolfy\Desktop\object_detection_demo-master\data\images\train\IMG_20200218_2038260.jpg</path>
	<source>
		<database>Unknown</database>
	</source>
	<size>
		<width>800</width>
		<height>600</height>
		<depth>3</depth>
	</size>
	<segmented>0</segmented>
	<object>
		<name>Jd</name>
		<pose>Unspecified</pose>
		<truncated>0</truncated>
		<difficult>0</difficult>
		<bndbox>
			<xmin>196</xmin>
			<ymin>123</ymin>
			<xmax>296</xmax>
			<ymax>168</ymax>
		</bndbox>
	</object>
	<object>
		<name>Jd</name>
		<pose>Unspecified</pose>
		<truncated>0</truncated>
		<difficult>0</difficult>
		<bndbox>
			<xmin>525</xmin>
			<ymin>142</ymin>
			<xmax>629</xmax>
			<ymax>183</ymax>
		</bndbox>
	</object>
	<object>
		<name>Jd</name>
		<pose>Unspecified</pose>
		<truncated>0</truncated>
		<difficult>0</difficult>
		<bndbox>
			<xmin>514</xmin>
			<ymin>384</ymin>
			<xmax>621</xmax>
			<ymax>428</ymax>
		</bndbox>
	</object>
	<object>
		<name>Jd</name>
		<pose>Unspecified</pose>
		<truncated>0</truncated>
		<difficult>0</difficult>
		<bndbox>
			<xmin>184</xmin>
			<ymin>367</ymin>
			<xmax>280</xmax>
			<ymax>408</ymax>
		</bndbox>
	</object>
</annotation>
