<annotation>
	<folder>prvi-deo</folder>
	<filename>IMG_20200218_204237.jpg</filename>
	<path>C:\Users\Marko\Desktop\prvi-deo\IMG_20200218_204237.jpg</path>
	<source>
		<database>Unknown</database>
	</source>
	<size>
		<width>800</width>
		<height>600</height>
		<depth>3</depth>
	</size>
	<segmented>0</segmented>
	<object>
		<name>Ah</name>
		<pose>Unspecified</pose>
		<truncated>0</truncated>
		<difficult>0</difficult>
		<bndbox>
			<xmin>184</xmin>
			<ymin>175</ymin>
			<xmax>295</xmax>
			<ymax>220</ymax>
		</bndbox>
	</object>
	<object>
		<name>Ah</name>
		<pose>Unspecified</pose>
		<truncated>0</truncated>
		<difficult>0</difficult>
		<bndbox>
			<xmin>558</xmin>
			<ymin>121</ymin>
			<xmax>680</xmax>
			<ymax>168</ymax>
		</bndbox>
	</object>
	<object>
		<name>Ah</name>
		<pose>Unspecified</pose>
		<truncated>0</truncated>
		<difficult>0</difficult>
		<bndbox>
			<xmin>212</xmin>
			<ymin>450</ymin>
			<xmax>326</xmax>
			<ymax>497</ymax>
		</bndbox>
	</object>
	<object>
		<name>Ah</name>
		<pose>Unspecified</pose>
		<truncated>0</truncated>
		<difficult>0</difficult>
		<bndbox>
			<xmin>600</xmin>
			<ymin>409</ymin>
			<xmax>726</xmax>
			<ymax>459</ymax>
		</bndbox>
	</object>
</annotation>
