<annotation>
	<folder>train</folder>
	<filename>IMG_20200217_224100.jpg</filename>
	<path>C:\Users\Woolfy\Desktop\object_detection_demo-master\data\images\train\IMG_20200217_224100.jpg</path>
	<source>
		<database>Unknown</database>
	</source>
	<size>
		<width>800</width>
		<height>600</height>
		<depth>3</depth>
	</size>
	<segmented>0</segmented>
	<object>
		<name>8s</name>
		<pose>Unspecified</pose>
		<truncated>0</truncated>
		<difficult>0</difficult>
		<bndbox>
			<xmin>418</xmin>
			<ymin>95</ymin>
			<xmax>517</xmax>
			<ymax>221</ymax>
		</bndbox>
	</object>
	<object>
		<name>8s</name>
		<pose>Unspecified</pose>
		<truncated>0</truncated>
		<difficult>0</difficult>
		<bndbox>
			<xmin>117</xmin>
			<ymin>290</ymin>
			<xmax>218</xmax>
			<ymax>423</ymax>
		</bndbox>
	</object>
</annotation>
